pycopyEcho/__init__.py
pycopyEcho/copy.py
pycopyEcho-0.1.0.dist-info/METADATA
pycopyEcho-0.1.0.dist-info/WHEEL
pycopyEcho-0.1.0.dist-info/top_level.txt
pycopyEcho-0.1.0.dist-info/RECORD
